iann/__init__.py
iann/__main__.py
iann/app.py
iann/controller.py
iann/models.py
iann/ui.py
iann/config/config.yaml
iann/data/__init__.py
iann/data/base.py
iann/data/compose.py
iann/data/points_sampler.py
iann/data/sample.py
iann/data/transforms.py
iann/data/datasets/__init__.py
iann/data/datasets/ade20k.py
iann/data/datasets/berkeley.py
iann/data/datasets/coco.py
iann/data/datasets/coco_lvis.py
iann/data/datasets/davis.py
iann/data/datasets/grabcut.py
iann/data/datasets/human.py
iann/data/datasets/images_dir.py
iann/data/datasets/lvis.py
iann/data/datasets/openimages.py
iann/data/datasets/pascalvoc.py
iann/data/datasets/sbd.py
iann/inference/__init__.py
iann/inference/clicker.py
iann/inference/evaluation.py
iann/inference/utils.py
iann/inference/predictor/__init__.py
iann/inference/predictor/base.py
iann/inference/predictor/brs.py
iann/inference/predictor/brs_functors.py
iann/inference/predictor/brs_losses.py
iann/inference/transforms/__init__.py
iann/inference/transforms/base.py
iann/inference/transforms/crops.py
iann/inference/transforms/flip.py
iann/inference/transforms/limit_longest_side.py
iann/inference/transforms/zoom_in.py
iann/model/__init__.py
iann/model/initializer.py
iann/model/is_deeplab_model.py
iann/model/is_hrnet_model.py
iann/model/is_model.py
iann/model/losses.py
iann/model/metrics.py
iann/model/modifiers.py
iann/model/ops.py
iann/model/modeling/__init__.py
iann/model/modeling/basic_blocks.py
iann/model/modeling/deeplab_v3.py
iann/model/modeling/hrnet_ocr.py
iann/model/modeling/ocr.py
iann/model/modeling/resnet.py
iann/model/modeling/resnetv1b.py
iann/resource/clear.png
iann/resource/finish.png
iann/resource/next.png
iann/resource/paddle.png
iann/resource/prev.png
iann/resource/redo.png
iann/resource/shortkey.jpg
iann/resource/undo.png
iann/util/__init__.py
iann/util/config.py
iann/util/distributed.py
iann/util/exp.py
iann/util/label.py
iann/util/misc.py
iann/util/network.py
iann/util/qt.py
iann/util/serialization.py
iann/util/vis.py
iann-0.1.2.dist-info/METADATA
iann-0.1.2.dist-info/WHEEL
iann-0.1.2.dist-info/entry_points.txt
iann-0.1.2.dist-info/top_level.txt
iann-0.1.2.dist-info/RECORD
