Metadata-Version: 2.1
Name: iann
Version: 0.1.2
Summary: 交互式标注软件
Home-page: https://github.com/PaddleCV-SIG/iann
Author: Paddlecv-SIG
Author-email: linhandev@qq.com
License: MIT
Platform: UNKNOWN
Classifier: License :: OSI Approved :: MIT License
Classifier: Programming Language :: Python :: 3
Classifier: Programming Language :: Python :: 3.8
Requires-Dist: pyqt5
Requires-Dist: qtpy
Requires-Dist: opencv-python
Requires-Dist: scipy
Requires-Dist: paddleseg
Requires-Dist: albumentations
Requires-Dist: cython
Requires-Dist: pyyaml
